muni2wasm/__init__.py
muni2wasm/__main__.py
muni2wasm/ast.py
muni2wasm/cli.py
muni2wasm/codegen_wat.py
muni2wasm/compiler.py
muni2wasm/env_python.py
muni2wasm/environment.py
muni2wasm/importer.py
muni2wasm/lexer.py
muni2wasm/parser.py
muni2wasm/semantics.py
muni2wasm/lib/math.mun
muni2wasm/lib/std.mun
muni2wasm/lib/std_dep/arrays.mun
muni2wasm/lib/std_dep/strings.mun
muni2wasm/lib/std_dep/vectors.mun
muni2wasm-0.1.3.post2.dist-info/licenses/LICENSE
muni2wasm-0.1.3.post2.dist-info/METADATA
muni2wasm-0.1.3.post2.dist-info/WHEEL
muni2wasm-0.1.3.post2.dist-info/entry_points.txt
muni2wasm-0.1.3.post2.dist-info/top_level.txt
muni2wasm-0.1.3.post2.dist-info/RECORD
