Metadata-Version: 2.4
Name: muni2wasm
Version: 0.1.3.post2
Summary: Muni compiler frontend targeting WebAssembly
Author-email: Azure Blondon <azure.blondon@gmail.com>
License-Expression: MIT
Requires-Python: >=3.7
License-File: LICENSE
Requires-Dist: wasmtime>=35.0.0
Requires-Dist: wabt>=0.1.2
Dynamic: license-file
